{"id":"amulet-2020","title":"Amulet","jump_scare_count":3,"runtime":99,"release_year":2020,"source_url":"https://wheresthejump.com/jump-scares-in-amulet-2020/","directors":["Romola Garai"],"jump_scares":[{"time_start":"00:35:52","time_stop":"00:35:57","spoiler":"The bat creature comes alive and bites Tomaz","major":false},{"time_start":"00:49:52","time_stop":"00:49:57","spoiler":"Magda is grabbed from behind","major":false},{"time_start":"01:03:19","time_stop":"01:03:24","spoiler":"Magda is stabbed through the hole","major":false}],"tags":[{"id":"haunted-house-building","name":"Haunted House / Building"},{"id":"religion-and-the-occult","name":"Religion \u0026 The Occult"},{"id":"low-jump-scare","name":"Low Jump Scare"}],"reviews":[{"name":"IMDb","url":"https://www.imdb.com/title/tt8332802/"},{"name":"Rotten Tomatoes","url":"https://www.rottentomatoes.com/m/amulet"}],"content_rating":"R"}
