{"id":"banshee-chapter-2013","title":"Banshee Chapter","jump_scare_count":22,"runtime":87,"release_year":2013,"source_url":"https://wheresthejump.com/jump-scares-in-banshee-chapter-2013/","details_url":"https://jumpy.wilhelm.codes/movies/banshee-chapter-2013.json","directors":["Blair Erickson"],"jump_scares":[{"time_start":"00:08:03","time_stop":"00:08:08","spoiler":"A shadowy figure passes the window behind James and the camera footage cuts out","major":false},{"time_start":"00:08:32","time_stop":"00:08:37","spoiler":"An image of James with a disfigured face briefly flashes across the camera footage","major":true},{"time_start":"00:13:46","time_stop":"00:13:51","spoiler":"A loud bang in an otherwise quiet scene may startle some people","major":false},{"time_start":"00:21:02","time_stop":"00:21:07","spoiler":"Anne shines the torch on a figure standing in the darkness","major":false},{"time_start":"00:27:13","time_stop":"00:27:18","spoiler":"An invisible force appears to drag Patient 11 away","major":false},{"time_start":"00:27:32","time_stop":"00:27:37","spoiler":"Patient 11 suddenly screams and pounds on the observation window","major":true},{"time_start":"00:41:53","time_stop":"00:41:58","spoiler":"Anne sees a mysterious figure standing by the window","major":false},{"time_start":"00:43:35","time_stop":"00:43:40","spoiler":"There is a loud bang followed by screaming","major":false},{"time_start":"00:43:45","time_stop":"00:43:50","spoiler":"Anne shines the torch on Callie who now has black eyes and is vomiting a red liquid","major":true},{"time_start":"00:47:17","time_stop":"00:47:22","spoiler":"Patient 14 begins to scream and shake violently","major":false},{"time_start":"00:48:59","time_stop":"00:49:04","spoiler":"Patient 14 suddenly appears in front of the scientist","major":true},{"time_start":"00:51:24","time_stop":"00:51:29","spoiler":"Anne looks in the car mirror and sees Thomas’s face has turned a red color","major":false},{"time_start":"01:02:05","time_stop":"01:02:10","spoiler":"A hand grabs Anne around the ankle as she walks up the stairs","major":true},{"time_start":"01:02:28","time_stop":"01:02:33","spoiler":"Thomas wakes up in the back seat and yells which startles Anne","major":false},{"time_start":"01:05:02","time_stop":"01:05:07","spoiler":"A researcher gets an electric shock","major":false},{"time_start":"01:05:51","time_stop":"01:05:56","spoiler":"The corpse on the examination table suddenly screams and grabs the researcher around the neck","major":false},{"time_start":"01:11:26","time_stop":"01:11:31","spoiler":"Anne looks into a hole built into the wall and a pale face with hollow eyes suddenly appears","major":true},{"time_start":"01:11:58","time_stop":"01:12:03","spoiler":"Anne looks down a corridor and sees an alien figure coming towards her","major":false},{"time_start":"01:13:18","time_stop":"01:13:23","spoiler":"Something begins to bang on the door","major":false},{"time_start":"01:13:55","time_stop":"01:14:00","spoiler":"A hand with long fingers suddenly appears on the locker that Anne is hiding in","major":false},{"time_start":"01:14:26","time_stop":"01:14:31","spoiler":"Anne turns around and sees a grotesque figure standing beside her","major":true},{"time_start":"01:21:21","time_stop":"01:21:26","spoiler":"Anne turns around and sees her friends face has the same black eyes and deformed expression as previous victims","major":false}],"tags":[{"id":"extraterrestrial-life","name":"Extraterrestrial Life","details_url":"https://jumpy.wilhelm.codes/tags/extraterrestrial-life.json"},{"id":"low-budget","name":"Low Budget","details_url":"https://jumpy.wilhelm.codes/tags/low-budget.json"},{"id":"mystery","name":"Mystery","details_url":"https://jumpy.wilhelm.codes/tags/mystery.json"},{"id":"high-jump-scare","name":"High Jump Scare","details_url":"https://jumpy.wilhelm.codes/tags/high-jump-scare.json"}],"reviews":[{"name":"IMDb","url":"https://www.imdb.com/title/tt2011276/"},{"name":"Rotten Tomatoes","url":"https://www.rottentomatoes.com/m/the_banshee_chapter/"}],"content_rating":"R","jump_scare_srt_url":"https://jumpy.wilhelm.codes/movies/banshee-chapter-2013.srt","jump_scare_spoilers_srt_url":"https://jumpy.wilhelm.codes/movies/banshee-chapter-2013-spoilers.srt"}
