{"id":"fear-street-part-three-1666-2021","title":"Fear Street Part Three: 1666","jump_scare_count":5,"runtime":114,"release_year":2021,"source_url":"https://wheresthejump.com/jump-scares-in-fear-street-part-three-1666-2021/","details_url":"https://jumpy.wilhelm.codes/movies/fear-street-part-three-1666-2021.json","directors":["Leigh Janiak"],"jump_scares":[{"time_start":"00:01:42","time_stop":"00:01:47","spoiler":"During the recap of the previous film, there is a loud cut to Sarah screaming at the camera","major":false},{"time_start":"00:45:32","time_stop":"00:45:37","spoiler":"A crow suddenly begins to flap and caw, startling Sarah","major":false},{"time_start":"01:21:49","time_stop":"01:21:54","spoiler":"A policeman appears behind Ziggy and Martin, startling them","major":false},{"time_start":"01:22:26","time_stop":"01:22:31","spoiler":"The policeman is suddenly stabbed","major":false},{"time_start":"01:41:40","time_stop":"01:41:45","spoiler":"As a car backs out of a driveway, a truck appears from the side of the screen and crashes into it","major":false}],"tags":[{"id":"book-adaptation","name":"Book Adaptation","details_url":"https://jumpy.wilhelm.codes/tags/book-adaptation.json"},{"id":"slasher","name":"Slasher","details_url":"https://jumpy.wilhelm.codes/tags/slasher.json"}],"reviews":[{"name":"IMDb","url":"https://www.imdb.com/title/tt9701942/"},{"name":"Rotten Tomatoes","url":"https://www.rottentomatoes.com/m/fear_street_part_three_1666"}],"content_rating":"R"}
