{"id":"seven-in-heaven-2018","title":"Seven in Heaven","jump_scare_count":8,"runtime":94,"release_year":2018,"source_url":"https://wheresthejump.com/jump-scares-in-seven-in-heaven-2018/","directors":["Chris Eigeman"],"jump_scares":[{"time_start":"00:23:19","time_stop":"00:23:24","spoiler":"A hand grabs Jude after he opens the door","major":false},{"time_start":"00:29:30","time_stop":"00:29:35","spoiler":"The counselor jumps out from behind a gravestone and punches Jude","major":false},{"time_start":"00:44:41","time_stop":"00:44:46","spoiler":"June jumps on Jude from a tree branch","major":false},{"time_start":"00:46:47","time_stop":"00:46:52","spoiler":"June turns on a light switch and it causes a lamp to explode","major":false},{"time_start":"00:50:41","time_stop":"00:50:46","spoiler":"As the kids are walking away a flashlight suddenly turns on in front of their faces","major":false},{"time_start":"00:54:23","time_stop":"00:54:28","spoiler":"Wallace grabs June’s hair","major":false},{"time_start":"00:58:33","time_stop":"00:58:38","spoiler":"As Jude looks towards Eric it suddenly cuts away to Eric jumping at him","major":false},{"time_start":"01:14:02","time_stop":"01:14:07","spoiler":"A deer flies through the car window, shattering it","major":false}],"tags":[{"id":"comedy","name":"Comedy"},{"id":"loner-misfit","name":"Loner / Misfit"},{"id":"sci-fi","name":"Sci-Fi"}],"reviews":[{"name":"IMDb","url":"https://www.imdb.com/title/tt4269118/"},{"name":"Rotten Tomatoes","url":"https://www.rottentomatoes.com/m/seven_in_heaven"}],"content_rating":"PG13"}
