{"id":"sputnik-2020","title":"Sputnik","jump_scare_count":3,"runtime":113,"release_year":2020,"source_url":"https://wheresthejump.com/jump-scares-in-sputnik-2020/","details_url":"https://jumpy.wilhelm.codes/movies/sputnik-2020.json","directors":["Egor Abramenko"],"jump_scares":[{"time_start":"00:25:37","time_stop":"00:25:42","spoiler":"While jogging, Tatyana suddenly runs into an inmate","major":false},{"time_start":"00:29:51","time_stop":"00:29:56","spoiler":"Tatyana places her hand on the window, and the alien suddenly lunges at the glass","major":false},{"time_start":"00:50:52","time_stop":"00:50:57","spoiler":"While reaching out to the alien, Tatyana suddenly slips on the goo on the floor and falls","major":false}],"tags":[{"id":"extraterrestrial-life","name":"Extraterrestrial Life","details_url":"https://jumpy.wilhelm.codes/tags/extraterrestrial-life.json"},{"id":"sci-fi","name":"Sci-Fi","details_url":"https://jumpy.wilhelm.codes/tags/sci-fi.json"},{"id":"low-jump-scare","name":"Low Jump Scare","details_url":"https://jumpy.wilhelm.codes/tags/low-jump-scare.json"}],"reviews":[{"name":"IMDb","url":"https://www.imdb.com/title/tt11905962/"},{"name":"Rotten Tomatoes","url":"https://www.rottentomatoes.com/m/sputnik_2020"}],"content_rating":"Unrated"}
