{"id":"the-cloverfield-paradox-2018","title":"The Cloverfield Paradox","jump_scare_count":8,"runtime":102,"release_year":2018,"source_url":"https://wheresthejump.com/jump-scares-in-the-cloverfield-paradox-2018/","details_url":"/movies/the-cloverfield-paradox-2018.json","directors":["Julius Onah"],"jump_scares":[{"time_start":"00:25:43","time_stop":"00:25:48","spoiler":"A strange shrieking noise resounds through the spaceship","major":false},{"time_start":"00:27:06","time_stop":"00:27:11","spoiler":"Tam puts her head up to the wall, after several seconds silence we hear the shrieking noise again accompanied by a thud from the other side of the wall","major":true},{"time_start":"00:27:50","time_stop":"00:27:55","spoiler":"A section of wall is removed to reveal a screaming woman who appears to be fused to the wiring of the space ship","major":false},{"time_start":"00:33:01","time_stop":"00:33:06","spoiler":"The Foosball figures start to spin rapidly by themselves","major":false},{"time_start":"00:34:46","time_stop":"00:34:51","spoiler":"Accompanied by a sound effect, Volkov’s eye moves while he is looking in the mirror","major":false},{"time_start":"00:38:04","time_stop":"00:38:09","spoiler":"Worms suddenly burst out of Volkov’s mouth","major":false},{"time_start":"00:46:08","time_stop":"00:46:13","spoiler":"The wall panel suddenly traps Mundy’s arm","major":false},{"time_start":"01:36:10","time_stop":"01:36:15","spoiler":"A monster bursts through the clouds","major":false}],"tags":[{"id":"extraterrestrial-life","name":"Extraterrestrial Life","details_url":"/tags/extraterrestrial-life.json"},{"id":"sci-fi","name":"Sci-Fi","details_url":"/tags/sci-fi.json"}],"reviews":[{"name":"IMDb","url":"https://www.imdb.com/title/tt2548396/"},{"name":"Rotten Tomatoes","url":"https://www.rottentomatoes.com/m/the_cloverfield_paradox/"}],"content_rating":"Unrated"}
