{"id":"the-swerve-2019","title":"The Swerve","runtime":96,"release_year":2019,"source_url":"https://wheresthejump.com/jump-scares-in-the-swerve-2019/","details_url":"https://jumpy.wilhelm.codes/movies/the-swerve-2019.json","directors":["Dean Kapsalis"],"tags":[{"id":"low-jump-scare","name":"Low Jump Scare","details_url":"https://jumpy.wilhelm.codes/tags/low-jump-scare.json"}],"reviews":[{"name":"IMDb","url":"https://www.imdb.com/title/tt7090638/"},{"name":"Rotten Tomatoes","url":"https://www.rottentomatoes.com/m/the_swerve"}],"content_rating":"Unrated"}
