{"id":"urban-legends-bloody-mary-2005","title":"Urban Legends: Bloody Mary","jump_scare_count":8,"runtime":93,"release_year":2005,"source_url":"https://wheresthejump.com/jump-scares-in-urban-legends-bloody-mary-2005/","details_url":"https://jumpy.wilhelm.codes/movies/urban-legends-bloody-mary-2005.json","directors":["Mary Lambert"],"jump_scares":[{"time_start":"00:12:09","time_stop":"00:12:14","spoiler":"As a person approaches the window from outside, there is a sudden flash with a loud noise","major":false},{"time_start":"00:36:31","time_stop":"00:36:36","spoiler":"Bloody Mary suddenly appears on the road while Tom is driving","major":false},{"time_start":"00:57:26","time_stop":"00:57:31","spoiler":"Bloody Mary grabs Buck from under the bed","major":false},{"time_start":"01:09:05","time_stop":"01:09:10","spoiler":"David is suddenly grabbed from behind with a plastic bag over his face","major":false},{"time_start":"01:12:17","time_stop":"01:12:22","spoiler":"While Samantha is walking, Bloody Mary suddenly flashes on the screen","major":false},{"time_start":"01:13:02","time_stop":"01:13:07","spoiler":"Samantha is startled by a steam pipe suddenly going off","major":false},{"time_start":"01:15:01","time_stop":"01:15:06","spoiler":"There is a sudden flash","major":false},{"time_start":"01:26:12","time_stop":"01:26:17","spoiler":"The camera cuts from Bill back to Bloody Mary to show her face has changed","major":false}],"tags":[{"id":"low-budget","name":"Low Budget","details_url":"https://jumpy.wilhelm.codes/tags/low-budget.json"},{"id":"paranormal","name":"Paranormal","details_url":"https://jumpy.wilhelm.codes/tags/paranormal.json"},{"id":"slasher","name":"Slasher","details_url":"https://jumpy.wilhelm.codes/tags/slasher.json"}],"reviews":[{"name":"IMDb","url":"https://www.imdb.com/title/tt0451957/"},{"name":"Rotten Tomatoes","url":"https://www.rottentomatoes.com/m/urban_legends_bloody_mary"}],"content_rating":"R","jump_scare_srt_url":"https://jumpy.wilhelm.codes/movies/urban-legends-bloody-mary-2005.srt","jump_scare_spoilers_srt_url":"https://jumpy.wilhelm.codes/movies/urban-legends-bloody-mary-2005-spoilers.srt"}
